[
  { "name": "01 - Getting Started",
    "url": "/Getting-Started",
    "description": "Setting up your own HTM-Elves workflow",
    "icon": "public/svg/env.svg"
  },
  { "name": "02 - Writing Your Own Tutorials",
    "url": "/Writing-Your-Own-Tutorials",
    "description": "Writing in Markdown using pre-defined snippets",
    "icon": "public/svg/pages.svg"
  },
  { "name": "03 - Building HTM-Elves from Scratch",
    "url": "/Building-From-Scratch",
    "description": "Understanding how HTM-Elves works, step-by-step, and learning how to customize it",
    "icon": "public/svg/tldr.svg"
  }
]